ubigeo/__init__.py
ubigeo/admin.py
ubigeo/apps.py
ubigeo/models.py
ubigeo/tests.py
ubigeo/views.py
ubigeo/fixtures/ubigeo.json
ubigeo/migrations/0001_initial.py
ubigeo/migrations/__init__.py
django_ubigeo-0.1.dist-info/LICENSE
django_ubigeo-0.1.dist-info/METADATA
django_ubigeo-0.1.dist-info/WHEEL
django_ubigeo-0.1.dist-info/top_level.txt
django_ubigeo-0.1.dist-info/RECORD
